secureli/__init__.py
secureli/actions/__init__.py
secureli/actions/action.py
secureli/actions/build.py
secureli/actions/initializer.py
secureli/actions/scan.py
secureli/actions/setup.py
secureli/actions/update.py
secureli/container.py
secureli/main.py
secureli/modules/__init__.py
secureli/modules/core/core_services/hook_scanner.py
secureli/modules/core/core_services/updater.py
secureli/modules/custom_scanners/custom_regex_scanner/custom_regex_scanner.py
secureli/modules/custom_scanners/custom_scans.py
secureli/modules/custom_scanners/pii_scanner/pii_scanner.py
secureli/modules/language_analyzer/__init__ .py
secureli/modules/language_analyzer/git_ignore.py
secureli/modules/language_analyzer/language_analyzer.py
secureli/modules/language_analyzer/language_config.py
secureli/modules/language_analyzer/language_support.py
secureli/modules/observability/consts/logging.py
secureli/modules/observability/observability_services/logging.py
secureli/modules/secureli_ignore.py
secureli/modules/shared/abstractions/__init__.py
secureli/modules/shared/abstractions/echo.py
secureli/modules/shared/abstractions/lexer_guesser.py
secureli/modules/shared/abstractions/pre_commit.py
secureli/modules/shared/abstractions/version_control_repo.py
secureli/modules/shared/consts/__init__.py
secureli/modules/shared/consts/language.py
secureli/modules/shared/consts/pii.py
secureli/modules/shared/consts/repository.py
secureli/modules/shared/models/__init__.py
secureli/modules/shared/models/config.py
secureli/modules/shared/models/echo.py
secureli/modules/shared/models/exit_codes.py
secureli/modules/shared/models/install.py
secureli/modules/shared/models/language.py
secureli/modules/shared/models/logging.py
secureli/modules/shared/models/publish_results.py
secureli/modules/shared/models/repository.py
secureli/modules/shared/models/result.py
secureli/modules/shared/models/scan.py
secureli/modules/shared/models/update.py
secureli/modules/shared/resources/__init__.py
secureli-0.42.1.dist-info/LICENSE
secureli-0.42.1.dist-info/METADATA
secureli-0.42.1.dist-info/WHEEL
secureli-0.42.1.dist-info/entry_points.txt
secureli-0.42.1.dist-info/RECORD
