Metadata-Version: 2.1
Name: secureli
Version: 0.42.1
Summary: Secure Project Manager
License: Apache-2.0
Author: Caleb Tonn
Author-email: caleb.tonn@slalom.com
Requires-Python: >=3.9,<3.12
Classifier: License :: OSI Approved :: Apache Software License
Classifier: Programming Language :: Python :: 3
Classifier: Programming Language :: Python :: 3.9
Classifier: Programming Language :: Python :: 3.10
Classifier: Programming Language :: Python :: 3.11
Requires-Dist: cfgv (>=3.3.1,<4.0.0)
Requires-Dist: chardet (>=5.2.0,<6.0.0)
Requires-Dist: dependency-injector[yaml] (>=4.40.0,<5.0.0)
Requires-Dist: gitpython (>=3.1.43,<4.0.0)
Requires-Dist: jinja2 (>=3.1.2,<4.0.0)
Requires-Dist: pathspec (>=0.10.1,<0.13.0)
Requires-Dist: pre-commit (>=2.20,<4.0)
Requires-Dist: pydantic (>=1.10.2,<2.0.0)
Requires-Dist: pygments (>=2.13.0,<3.0.0)
Requires-Dist: pyyaml (>=6.0.1)
Requires-Dist: requests (>=2.31.0,<3.0.0)
Requires-Dist: typer[all] (>=0.6.1,<0.13.0)
